flask_tailwind/__init__.py
flask_tailwind/cli.py
flask_tailwind/console.py
flask_tailwind/py.typed
flask_tailwind/tailwind.py
flask_tailwind/starter/.gitignore
flask_tailwind/starter/package.json
flask_tailwind/starter/src/input.css
flask_tailwind/templates/input.css.jinja
flask_tailwind/templates/load.jinja
flask_tailwind/templates/package.json.jinja
flask_tailwind_manager-0.0.20.dist-info/licenses/LICENSE
flask_tailwind_manager-0.0.20.dist-info/METADATA
flask_tailwind_manager-0.0.20.dist-info/WHEEL
flask_tailwind_manager-0.0.20.dist-info/top_level.txt
flask_tailwind_manager-0.0.20.dist-info/RECORD
