Metadata-Version: 2.4
Name: flask-tailwind-manager
Version: 0.0.20
Summary: Easily use tailwind css with Flask projects
Author-email: Sebastian Salinas <seba.salinas.delrio@gmail.com>
License: MIT
Project-URL: Homepage, https://github.com/sebasalinass/flask-leaflet
Keywords: flask,tailwind,tailwindcss
Classifier: Programming Language :: Python
Classifier: Programming Language :: Python :: 3
Requires-Python: >=3.9
License-File: LICENSE
Requires-Dist: flask<4,>=2
Dynamic: license-file
